lib/__init__.py
lib/dhruv.py
Topsis1_dhruv_102103462-0.0.1.dist-info/METADATA
Topsis1_dhruv_102103462-0.0.1.dist-info/WHEEL
Topsis1_dhruv_102103462-0.0.1.dist-info/top_level.txt
Topsis1_dhruv_102103462-0.0.1.dist-info/RECORD
